{
    "general":
    [
        {
            "No" : "0",
            "Keyword" : "Founding",
            "Question": "Wann wurde die Maschinenfabrik Reinhausen gegruendet",
            "answers":
            [
                {
                    "ID" : "a",
                    "Answer": "1929",
                    "truth": true
                },
                {
                    "ID" : "b",
                    "Answer": "1986",
                    "truth" : false
                },
                {
                    "ID" : "c",
                    "Answer": "1999",
                    "truth" : false
                }
            ]
        },
        {
            "No" : "1",
            "Keyword" : "Founding Members",
            "Question" : "Wer waren die Gruendungsmitglieder der MR?",
            "answers":
            [
                {
                    "ID" : "a",
                    "Answer": "Karl Rapp und Gustav Otto",
                    "truth": false
                },
                {
                    "ID" : "b",
                    "Answer": "Nikola Teasla und Thomas Edison",
                    "truth" : false
                },
                {
                    "ID" : "c",
                    "Answer": "Die Gebr체der Scheubeck",
                    "truth" : true
                }
            ]
        },
        {
            "No": "2",
            "Keyword" : "Invention Tap Changer",
            "Question" : "Wann wurde der erste Laststufenschalter erfunden?",
            "answers":
            [
                {
                    "ID" : "a",
                    "Answer": "1929",
                    "truth": true
                },
                {
                    "ID" : "b",
                    "Answer": "1672",
                    "truth" : false
                },
                {
                    "ID" : "c",
                    "Answer": "1847",
                    "truth" : false
                }
            ]
        },
        {
            "No": "3",
            "Keyword" : "Company Locations",
            "Question" : "In wie vielen Laendern sind wir vertreten?",
            "answers":
            [
                {
                    "ID" : "a",
                    "Answer": "130",
                    "truth": false
                },
                {
                    "ID" : "b",
                    "Answer": "13",
                    "truth" : false
                },
                {
                    "ID" : "c",
                    "Answer": "28",
                    "truth" : true
                }
            ]
        },
        {
            "No": "4",
            "Keyword" : "Training offers",
            "Question" : "wie viele Ausbildungsangebote gibt es?",
            "answers":
            [
                {
                    "ID" : "a",
                    "Answer": "None",
                    "truth": false
                },
                {
                    "ID" : "b",
                    "Answer": "None",
                    "truth" : false
                },
                {
                    "ID" : "c",
                    "Answer": "9",
                    "truth" : true
                }
            ]
        },
        {
            "No": "5",
            "Keyword" : "Advantages",
            "Question" : "Was sind deine Vorteile w채hrend der Ausbildung?",
            "answers":
            [
                {
                    "ID" : "a",
                    "Answer": "35-Stunden Woche",
                    "truth": true
                },
                {
                    "ID" : "b",
                    "Answer": "iPad oder Laptop",
                    "truth" : true
                },
                {
                    "ID" : "c",
                    "Answer": "akktraktive Verg체nstigungen",
                    "truth" : true
                }
            ]
        },
        {
            "No": "6",
            "Keyword" : "Number of trainees",
            "Question" : "Wie viele Auszubildende werden derzeit in der MR auf die spaeteren Unternehmensaufgaben vorbereitet?",
            "answers":
            [
                {
                    "ID" : "a",
                    "Answer": "None",
                    "truth": true
                },
                {
                    "ID" : "b",
                    "Answer": "None",
                    "truth" : false
                },
                {
                    "ID" : "c",
                    "Answer": "None",
                    "truth" : false
                }
            ]
        }
    ],

    "Electro_IT":
    [
        {
            "No" : "0",
            "Keyword" : "Hardware",
            "Question": "Was versteht man unter Hardware?",
            "answers":
            [
                {
                    "ID" : "a",
                    "Answer": "Eisen, Kunststoff, ...",
                    "truth": false
                },
                {
                    "ID" : "b",
                    "Answer": "Elektronische Bauteile eines Computers",
                    "truth" : true
                },
                {
                    "ID" : "c",
                    "Answer": "Betriebssysteme wie Windows oder Linux",
                    "truth" : false
                }
            ]
        },

        {
            "No" : "1",
            "Keyword" : "Software",
            "Question": "Was versteht man unter Software?",
            "answers":
            [
                {
                    "ID" : "a",
                    "Answer": "Betriebssystem, Programme und Anwendungen",
                    "truth": true
                },
                {
                    "ID" : "b",
                    "Answer": "Schaumstoff",
                    "truth" : false
                },
                {
                    "ID" : "c",
                    "Answer": "L체fter",
                    "truth" : false
                }
            ]
        },

        {
            "No" : "2",
            "Keyword" : "CPU",
            "Question": "Was bedeutet CPU?",
            "answers":
            [
                {
                    "ID" : "a",
                    "Answer": "Grafikkarte",
                    "truth": false
                },
                {
                    "ID" : "b",
                    "Answer": "Prozessor",
                    "truth" : true
                },
                {
                    "ID" : "c",
                    "Answer": "Netzteil",
                    "truth" : false
                }
            ]
        },

        {
            "No" : "3",
            "Keyword" : "Storage",
            "Question": "Worauf kann man Daten dauerhaft abspeichern?",
            "answers":
            [
                {
                    "ID" : "a",
                    "Answer": "Arbeitsspeicher",
                    "truth": true
                },
                {
                    "ID" : "b",
                    "Answer": "Festplatte (SSD, HDD)",
                    "truth" : false
                },
                {
                    "ID" : "c",
                    "Answer": "Cache",
                    "truth" : false
                }
            ]
        }
    ]
}